StackX.py
stackx-1.0.0.dist-info/WHEEL
stackx-1.0.0.dist-info/METADATA
stackx-1.0.0.dist-info/RECORD
